pysqoop/MapredJob.py
pysqoop/SqoopImport.py
pysqoop/SqoopJob.py
pysqoop/__init__.py
pysqoop-0.0.16.dist-info/LICENSE
pysqoop-0.0.16.dist-info/METADATA
pysqoop-0.0.16.dist-info/WHEEL
pysqoop-0.0.16.dist-info/top_level.txt
pysqoop-0.0.16.dist-info/RECORD
