Metadata-Version: 2.1
Name: pysqoop
Version: 0.0.16
Summary: A simple package to let you Sqoop into HDFS/Hive/HBase with python
Home-page: https://github.com/lucafon/pysqoop
Author: Luca Fontanili
Author-email: luca.fontanili93@gmail.com
License: UNKNOWN
Platform: UNKNOWN
Classifier: Programming Language :: Python :: 3
Classifier: License :: OSI Approved :: MIT License
Classifier: Operating System :: OS Independent
